setup.py
src/1c3o3cxj.egg-info/PKG-INFO
src/1c3o3cxj.egg-info/SOURCES.txt
src/1c3o3cxj.egg-info/dependency_links.txt
src/1c3o3cxj.egg-info/top_level.txt
src/HHH/__init__.py
src/HHH/brave/__init__.py
src/HHH/brave/sunny/__init__.py
src/HHH/brave/sunny/information.py
src/HHH/brave/sunny/message.py