Metadata-Version: 2.1
Name: 1c3o3cxj
Version: 0.4
Summary: 袁力祈,何慧华
Author: HHH
License: UNKNOWN
Platform: UNKNOWN
